zosftplib.py
zosftplib-2.0.dist-info/METADATA
zosftplib-2.0.dist-info/WHEEL
zosftplib-2.0.dist-info/top_level.txt
zosftplib-2.0.dist-info/RECORD
