Metadata-Version: 2.1
Name: zosftplib
Version: 2.0
Summary: z/OS Mainframe ftplib subclass
Home-page: http://www.datim.fr
Author: Denis Wallerich
Author-email: denis.wallerich@datim.fr
License: BSD
Platform: UNKNOWN
Classifier: Programming Language :: Python :: 3
Classifier: Development Status :: 4 - Beta
Classifier: Topic :: System :: Hardware :: Mainframes
Classifier: Topic :: Internet :: File Transfer Protocol (FTP)
Classifier: Topic :: Software Development :: Libraries
Classifier: License :: OSI Approved :: BSD License
Classifier: Operating System :: OS Independent
